oeg_iv/__init__.py
oeg_iv/orientation.py
oeg_iv/csvfile/README.md
oeg_iv/csvfile/__init__.py
oeg_iv/csvfile/row.py
oeg_iv/csvfile/tubes.py
oeg_iv-1.9.3.dist-info/LICENSE
oeg_iv-1.9.3.dist-info/METADATA
oeg_iv-1.9.3.dist-info/WHEEL
oeg_iv-1.9.3.dist-info/top_level.txt
oeg_iv-1.9.3.dist-info/RECORD
