Metadata-Version: 2.1
Name: oeg-iv
Version: 1.9.3
Summary: Python package for communication with InspectionViewer app
Home-page: https://github.com/vb64/oeg.iv
Author: Vitaly Bogomolov
Author-email: mail@vitaly-bogomolov.ru
License: UNKNOWN
Project-URL: Bug Tracker, https://github.com/vb64/oeg.iv/issues
Platform: UNKNOWN
Classifier: Programming Language :: Python
Classifier: License :: OSI Approved :: GNU General Public License v3 (GPLv3)
Classifier: Operating System :: OS Independent
Requires-Dist: py23
